terminal_tetris/__init__.py
terminal_tetris/main.py
terminal_tetris/menu_quotes.txt
terminal_tetris/assets/drop.mp3
terminal_tetris/assets/drop2.mp3
terminal_tetris/assets/drop3.mp3
terminal_tetris/assets/music.mp3
terminal_tetris/assets/pop.mp3
terminal_tetris/assets/slide.mp3
terminal_tetris-0.0.7.dist-info/METADATA
terminal_tetris-0.0.7.dist-info/WHEEL
terminal_tetris-0.0.7.dist-info/entry_points.txt
terminal_tetris-0.0.7.dist-info/licenses/LICENSE
terminal_tetris-0.0.7.dist-info/RECORD
