Metadata-Version: 2.4
Name: terminal-tetris
Version: 0.0.7
Summary: A feature-rich terminal-based Tetris game written in Python.
Project-URL: Homepage, https://github.com/averyvisentin/terminal-tetris
Project-URL: Bug Tracker, https://github.com/averyvisentin/terminal-tetris/issues
Author-email: Avery Visentin <averyvisentin@gmail.com>
License-File: LICENSE
Classifier: License :: OSI Approved :: MIT License
Classifier: Operating System :: OS Independent
Classifier: Programming Language :: Python :: 3
Requires-Python: >=3.7
Requires-Dist: blessed
